eqjson/__init__.py
eqjson/eqjson.py
eqjson-1.0.1.dist-info/DESCRIPTION.rst
eqjson-1.0.1.dist-info/METADATA
eqjson-1.0.1.dist-info/RECORD
eqjson-1.0.1.dist-info/WHEEL
eqjson-1.0.1.dist-info/metadata.json
eqjson-1.0.1.dist-info/top_level.txt
