Metadata-Version: 2.0
Name: eqjson
Version: 1.0.1
Summary: An smart json,similar to the jquery, read and update the json data
Home-page: https://github.com/tinybees/eqjson
Author: TinyBees
Author-email: a598824322@qq.com
License: MIT
Keywords: parser json eqjson query update
Platform: UNKNOWN
Classifier: Development Status :: 5 - Production/Stable
Classifier: Intended Audience :: Developers
Classifier: License :: OSI Approved :: MIT License
Classifier: Natural Language :: Chinese (Simplified)
Classifier: Operating System :: POSIX
Classifier: Operating System :: Microsoft :: Windows
Classifier: Operating System :: MacOS :: MacOS X
Classifier: Topic :: Software Development :: Libraries :: Python Modules
Classifier: Topic :: Utilities
Classifier: Programming Language :: Python
Classifier: Programming Language :: Python :: 3.5
Classifier: Programming Language :: Python :: 3.6
Requires-Python: >=3.5
